ovos_PHAL_plugin_mk2/__init__.py
ovos_PHAL_plugin_mk2/version.py
ovos_PHAL_plugin_mk2-0.0.1a4.dist-info/METADATA
ovos_PHAL_plugin_mk2-0.0.1a4.dist-info/WHEEL
ovos_PHAL_plugin_mk2-0.0.1a4.dist-info/entry_points.txt
ovos_PHAL_plugin_mk2-0.0.1a4.dist-info/top_level.txt
ovos_PHAL_plugin_mk2-0.0.1a4.dist-info/zip-safe
ovos_PHAL_plugin_mk2-0.0.1a4.dist-info/RECORD
