Metadata-Version: 2.1
Name: ovos-PHAL-plugin-mk2
Version: 0.0.1a4
Summary: A PHAL plugin for mycroft
Home-page: https://github.com/OpenVoiceOS/ovos-PHAL-plugin-mk2
Author: JarbasAi
Author-email: jarbasai@mailfence.com
License: Apache-2.0
Platform: UNKNOWN
Classifier: Development Status :: 3 - Alpha
Classifier: Intended Audience :: Developers
Classifier: Topic :: Text Processing :: Linguistic
Classifier: License :: OSI Approved :: Apache Software License
Classifier: Programming Language :: Python :: 3.5
Classifier: Programming Language :: Python :: 3.6
Requires-Dist: ovos-plugin-manager
Requires-Dist: sj201-interface
